{
  "metadata": {
    "type": "gainers_rankings_only",
    "total_symbols": 57,
    "generated_at": "2025-09-26T11:23:35.104642",
    "source": "Binance Futures API",
    "description": "Gainers排行榜前60名（纯排行榜数据，无K线）"
  },
  "rankings": [
    {
      "rank": 1,
      "symbol": "SQDUSDT",
      "market_data": {
        "symbol": "SQDUSDT",
        "base_asset": "SQD",
        "quote_asset": "USDT",
        "price": 0.20166,
        "high_price": 0.20549,
        "low_price": 0.07962,
        "volume_24h": {
          "base_volume": 3402961772.0,
          "quote_volume": 449963568.21694,
          "count": 4723960
        },
        "change_24h": {
          "absolute": 0.11926,
          "percentage": 143.514
        },
        "open_price": 0.0831,
        "prev_close_price": 0.0831,
        "bid_price": 0.20079,
        "ask_price": 0.201,
        "bid_qty": 50.0,
        "ask_qty": 68.0,
        "mark_price": 0.20153,
        "funding_rate": -0.00132168,
        "next_funding_time": 1758888000000,
        "open_interest": 4723960.0,
        "timestamp": 1758885814075,
        "market_cap": null,
        "circulating_supply": null,
        "market_cap_rank": null
      }
    },
    {
      "rank": 2,
      "symbol": "XPLUSDT",
      "market_data": {
        "symbol": "XPLUSDT",
        "base_asset": "XPL",
        "quote_asset": "USDT",
        "price": 1.1724,
        "high_price": 1.45,
        "low_price": 0.6846,
        "volume_24h": {
          "base_volume": 7681787878.0,
          "quote_volume": 8249675929.6738,
          "count": 24630277
        },
        "change_24h": {
          "absolute": 0.3643,
          "percentage": 45.02
        },
        "open_price": 0.8092,
        "prev_close_price": 0.8092,
        "bid_price": 1.1714,
        "ask_price": 1.1716,
        "bid_qty": 560.0,
        "ask_qty": 971.0,
        "mark_price": 1.17180821,
        "funding_rate": 0.0002003,
        "next_funding_time": 1758888000000,
        "open_interest": 24630277.0,
        "timestamp": 1758885814072,
        "market_cap": null,
        "circulating_supply": null,
        "market_cap_rank": null
      }
    },
    {
      "rank": 3,
      "symbol": "SNXUSDT",
      "market_data": {
        "symbol": "SNXUSDT",
        "base_asset": "SNX",
        "quote_asset": "USDT",
        "price": 0.919,
        "high_price": 0.969,
        "low_price": 0.774,
        "volume_24h": {
          "base_volume": 219298496.6,
          "quote_volume": 187901490.1,
          "count": 638770
        },
        "change_24h": {
          "absolute": 0.139,
          "percentage": 17.821
        },
        "open_price": 0.78,
        "prev_close_price": 0.78,
        "bid_price": 0.919,
        "ask_price": 0.92,
        "bid_qty": 13466.2,
        "ask_qty": 2513.1,
        "mark_price": 0.91963276,
        "funding_rate": 0.0001,
        "next_funding_time": 1758902400000,
        "open_interest": 638770.0,
        "timestamp": 1758885814073,
        "market_cap": null,
        "circulating_supply": null,
        "market_cap_rank": null
      }
    },
    {
      "rank": 4,
      "symbol": "AIAUSDT",
      "market_data": {
        "symbol": "AIAUSDT",
        "base_asset": "AIA",
        "quote_asset": "USDT",
        "price": 0.31279,
        "high_price": 0.32419,
        "low_price": 0.25283,
        "volume_24h": {
          "base_volume": 291874990.0,
          "quote_volume": 82347417.80512,
          "count": 1760361
        },
        "change_24h": {
          "absolute": 0.04262,
          "percentage": 15.792
        },
        "open_price": 0.26989,
        "prev_close_price": 0.26989,
        "bid_price": 0.31342,
        "ask_price": 0.31345,
        "bid_qty": 270.0,
        "ask_qty": 210.0,
        "mark_price": 0.31327,
        "funding_rate": 0.00028271,
        "next_funding_time": 1758888000000,
        "open_interest": 1760361.0,
        "timestamp": 1758885814075,
        "market_cap": null,
        "circulating_supply": null,
        "market_cap_rank": null
      }
    },
    {
      "rank": 5,
      "symbol": "HIPPOUSDT",
      "market_data": {
        "symbol": "HIPPOUSDT",
        "base_asset": "HIPPO",
        "quote_asset": "USDT",
        "price": 0.003319,
        "high_price": 0.003421,
        "low_price": 0.002808,
        "volume_24h": {
          "base_volume": 36601281405.0,
          "quote_volume": 115019272.224501,
          "count": 970051
        },
        "change_24h": {
          "absolute": 0.000445,
          "percentage": 15.489
        },
        "open_price": 0.002873,
        "prev_close_price": 0.002873,
        "bid_price": 0.003322,
        "ask_price": 0.003323,
        "bid_qty": 6773.0,
        "ask_qty": 57657.0,
        "mark_price": 0.00331674,
        "funding_rate": 0.00071631,
        "next_funding_time": 1758888000000,
        "open_interest": 970051.0,
        "timestamp": 1758885814074,
        "market_cap": null,
        "circulating_supply": null,
        "market_cap_rank": null
      }
    },
    {
      "rank": 6,
      "symbol": "TRADOORUSDT",
      "market_data": {
        "symbol": "TRADOORUSDT",
        "base_asset": "TRADOOR",
        "quote_asset": "USDT",
        "price": 2.635,
        "high_price": 2.767,
        "low_price": 2.222,
        "volume_24h": {
          "base_volume": 16731650.0,
          "quote_volume": 42272942.47,
          "count": 424069
        },
        "change_24h": {
          "absolute": 0.311,
          "percentage": 13.371
        },
        "open_price": 2.326,
        "prev_close_price": 2.326,
        "bid_price": 2.634,
        "ask_price": 2.635,
        "bid_qty": 151.0,
        "ask_qty": 317.0,
        "mark_price": 2.63449482,
        "funding_rate": 5e-05,
        "next_funding_time": 1758888000000,
        "open_interest": 424069.0,
        "timestamp": 1758885814073,
        "market_cap": 36770928.0,
        "circulating_supply": 14349000.0,
        "market_cap_rank": 933
      }
    },
    {
      "rank": 7,
      "symbol": "CUDISUSDT",
      "market_data": {
        "symbol": "CUDISUSDT",
        "base_asset": "CUDIS",
        "quote_asset": "USDT",
        "price": 0.09331,
        "high_price": 0.1188,
        "low_price": 0.07802,
        "volume_24h": {
          "base_volume": 702735832.0,
          "quote_volume": 72097074.65011,
          "count": 680866
        },
        "change_24h": {
          "absolute": 0.01073,
          "percentage": 13.0
        },
        "open_price": 0.08254,
        "prev_close_price": 0.08254,
        "bid_price": 0.09326,
        "ask_price": 0.09331,
        "bid_qty": 23.0,
        "ask_qty": 2835.0,
        "mark_price": 0.09335145,
        "funding_rate": -0.00379253,
        "next_funding_time": 1758888000000,
        "open_interest": 680866.0,
        "timestamp": 1758885814073,
        "market_cap": 23292039.0,
        "circulating_supply": 247500000.0,
        "market_cap_rank": 1211
      }
    },
    {
      "rank": 8,
      "symbol": "SKATEUSDT",
      "market_data": {
        "symbol": "SKATEUSDT",
        "base_asset": "SKATE",
        "quote_asset": "USDT",
        "price": 0.05266,
        "high_price": 0.06034,
        "low_price": 0.04516,
        "volume_24h": {
          "base_volume": 573299658.0,
          "quote_volume": 30164303.92637,
          "count": 324353
        },
        "change_24h": {
          "absolute": 0.00566,
          "percentage": 12.045
        },
        "open_price": 0.04699,
        "prev_close_price": 0.04699,
        "bid_price": 0.05265,
        "ask_price": 0.05269,
        "bid_qty": 4834.0,
        "ask_qty": 4053.0,
        "mark_price": 0.05257013,
        "funding_rate": 7.747e-05,
        "next_funding_time": 1758888000000,
        "open_interest": 324353.0,
        "timestamp": 1758885814073,
        "market_cap": 11400150.0,
        "circulating_supply": 213849008.80420306,
        "market_cap_rank": 1658
      }
    },
    {
      "rank": 9,
      "symbol": "ZROUSDT",
      "market_data": {
        "symbol": "ZROUSDT",
        "base_asset": "ZRO",
        "quote_asset": "USDT",
        "price": 2.2441,
        "high_price": 2.3422,
        "low_price": 1.9676,
        "volume_24h": {
          "base_volume": 44213297.1,
          "quote_volume": 96671057.16092,
          "count": 1100522
        },
        "change_24h": {
          "absolute": 0.2253,
          "percentage": 11.16
        },
        "open_price": 2.0189,
        "prev_close_price": 2.0189,
        "bid_price": 2.244,
        "ask_price": 2.2441,
        "bid_qty": 242.9,
        "ask_qty": 10.0,
        "mark_price": 2.24470904,
        "funding_rate": 5e-05,
        "next_funding_time": 1758888000000,
        "open_interest": 1100522.0,
        "timestamp": 1758885814075,
        "market_cap": null,
        "circulating_supply": null,
        "market_cap_rank": null
      }
    },
    {
      "rank": 10,
      "symbol": "BARDUSDT",
      "market_data": {
        "symbol": "BARDUSDT",
        "base_asset": "BARD",
        "quote_asset": "USDT",
        "price": 1.1775,
        "high_price": 1.2084,
        "low_price": 0.9861,
        "volume_24h": {
          "base_volume": 347802343.0,
          "quote_volume": 386977322.1127,
          "count": 5366851
        },
        "change_24h": {
          "absolute": 0.1174,
          "percentage": 11.086
        },
        "open_price": 1.059,
        "prev_close_price": 1.059,
        "bid_price": 1.1776,
        "ask_price": 1.1777,
        "bid_qty": 217.0,
        "ask_qty": 1989.0,
        "mark_price": 1.17651065,
        "funding_rate": 5e-05,
        "next_funding_time": 1758888000000,
        "open_interest": 5366851.0,
        "timestamp": 1758885814073,
        "market_cap": null,
        "circulating_supply": null,
        "market_cap_rank": null
      }
    },
    {
      "rank": 11,
      "symbol": "STGUSDT",
      "market_data": {
        "symbol": "STGUSDT",
        "base_asset": "STG",
        "quote_asset": "USDT",
        "price": 0.1936,
        "high_price": 0.2008,
        "low_price": 0.1704,
        "volume_24h": {
          "base_volume": 140323099.0,
          "quote_volume": 26514442.5158,
          "count": 191053
        },
        "change_24h": {
          "absolute": 0.0189,
          "percentage": 10.819
        },
        "open_price": 0.1747,
        "prev_close_price": 0.1747,
        "bid_price": 0.1935,
        "ask_price": 0.1936,
        "bid_qty": 27119.0,
        "ask_qty": 8700.0,
        "mark_price": 0.19352995,
        "funding_rate": -0.00027198,
        "next_funding_time": 1758902400000,
        "open_interest": 191053.0,
        "timestamp": 1758885814075,
        "market_cap": null,
        "circulating_supply": null,
        "market_cap_rank": null
      }
    },
    {
      "rank": 12,
      "symbol": "ARCUSDT",
      "market_data": {
        "symbol": "ARCUSDT",
        "base_asset": "ARC",
        "quote_asset": "USDT",
        "price": 0.02013,
        "high_price": 0.02069,
        "low_price": 0.01712,
        "volume_24h": {
          "base_volume": 1204631400.0,
          "quote_volume": 23167098.19438,
          "count": 199462
        },
        "change_24h": {
          "absolute": 0.0019,
          "percentage": 10.422
        },
        "open_price": 0.01823,
        "prev_close_price": 0.01823,
        "bid_price": 0.02012,
        "ask_price": 0.02014,
        "bid_qty": 47907.0,
        "ask_qty": 22952.0,
        "mark_price": 0.02013,
        "funding_rate": 0.00020946,
        "next_funding_time": 1758888000000,
        "open_interest": 199462.0,
        "timestamp": 1758885814074,
        "market_cap": null,
        "circulating_supply": null,
        "market_cap_rank": null
      }
    },
    {
      "rank": 13,
      "symbol": "SPKUSDT",
      "market_data": {
        "symbol": "SPKUSDT",
        "base_asset": "SPK",
        "quote_asset": "USDT",
        "price": 0.0515,
        "high_price": 0.05893,
        "low_price": 0.04573,
        "volume_24h": {
          "base_volume": 5000419906.0,
          "quote_volume": 267692232.82294,
          "count": 2130140
        },
        "change_24h": {
          "absolute": 0.00434,
          "percentage": 9.207
        },
        "open_price": 0.04714,
        "prev_close_price": 0.04714,
        "bid_price": 0.05148,
        "ask_price": 0.05149,
        "bid_qty": 1070.0,
        "ask_qty": 7843.0,
        "mark_price": 0.05149052,
        "funding_rate": -0.00151202,
        "next_funding_time": 1758888000000,
        "open_interest": 2130140.0,
        "timestamp": 1758885814073,
        "market_cap": null,
        "circulating_supply": null,
        "market_cap_rank": null
      }
    },
    {
      "rank": 14,
      "symbol": "1000SATSUSDT",
      "market_data": {
        "symbol": "1000SATSUSDT",
        "base_asset": "1000SATS",
        "quote_asset": "USDT",
        "price": 4.27e-05,
        "high_price": 4.36e-05,
        "low_price": 3.68e-05,
        "volume_24h": {
          "base_volume": 2736334596314.0,
          "quote_volume": 110188308.854726,
          "count": 287581
        },
        "change_24h": {
          "absolute": 3.6e-06,
          "percentage": 9.207
        },
        "open_price": 3.91e-05,
        "prev_close_price": 3.91e-05,
        "bid_price": 4.26e-05,
        "ask_price": 4.27e-05,
        "bid_qty": 1100125177.0,
        "ask_qty": 103365887.0,
        "mark_price": 4.267e-05,
        "funding_rate": 5e-05,
        "next_funding_time": 1758888000000,
        "open_interest": 287581.0,
        "timestamp": 1758885814075,
        "market_cap": null,
        "circulating_supply": null,
        "market_cap_rank": null
      }
    },
    {
      "rank": 15,
      "symbol": "DEGOUSDT",
      "market_data": {
        "symbol": "DEGOUSDT",
        "base_asset": "DEGO",
        "quote_asset": "USDT",
        "price": 1.3161,
        "high_price": 1.3548,
        "low_price": 1.1962,
        "volume_24h": {
          "base_volume": 8724895.4,
          "quote_volume": 11310675.76774,
          "count": 192354
        },
        "change_24h": {
          "absolute": 0.1093,
          "percentage": 9.041
        },
        "open_price": 1.2089,
        "prev_close_price": 1.2089,
        "bid_price": 1.316,
        "ask_price": 1.317,
        "bid_qty": 296.8,
        "ask_qty": 44.1,
        "mark_price": 1.3163,
        "funding_rate": 5e-05,
        "next_funding_time": 1758888000000,
        "open_interest": 192354.0,
        "timestamp": 1758885814074,
        "market_cap": null,
        "circulating_supply": null,
        "market_cap_rank": null
      }
    },
    {
      "rank": 16,
      "symbol": "EPTUSDT",
      "market_data": {
        "symbol": "EPTUSDT",
        "base_asset": "EPT",
        "quote_asset": "USDT",
        "price": 0.005037,
        "high_price": 0.005333,
        "low_price": 0.004434,
        "volume_24h": {
          "base_volume": 2100896170.0,
          "quote_volume": 10452957.092651,
          "count": 133012
        },
        "change_24h": {
          "absolute": 0.000394,
          "percentage": 8.486
        },
        "open_price": 0.004643,
        "prev_close_price": 0.004643,
        "bid_price": 0.00503,
        "ask_price": 0.005037,
        "bid_qty": 58245.0,
        "ask_qty": 22354.0,
        "mark_price": 0.00503219,
        "funding_rate": 0.00028945,
        "next_funding_time": 1758888000000,
        "open_interest": 133012.0,
        "timestamp": 1758885814073,
        "market_cap": null,
        "circulating_supply": null,
        "market_cap_rank": null
      }
    },
    {
      "rank": 17,
      "symbol": "TAUSDT",
      "market_data": {
        "symbol": "TAUSDT",
        "base_asset": "TA",
        "quote_asset": "USDT",
        "price": 0.0719,
        "high_price": 0.0732,
        "low_price": 0.06413,
        "volume_24h": {
          "base_volume": 228259779.0,
          "quote_volume": 15449510.353,
          "count": 239598
        },
        "change_24h": {
          "absolute": 0.00542,
          "percentage": 8.147
        },
        "open_price": 0.06653,
        "prev_close_price": 0.06653,
        "bid_price": 0.0719,
        "ask_price": 0.07191,
        "bid_qty": 75.0,
        "ask_qty": 9006.0,
        "mark_price": 0.07186289,
        "funding_rate": 0.00020935,
        "next_funding_time": 1758888000000,
        "open_interest": 239598.0,
        "timestamp": 1758885814072,
        "market_cap": null,
        "circulating_supply": null,
        "market_cap_rank": null
      }
    },
    {
      "rank": 18,
      "symbol": "TANSSIUSDT",
      "market_data": {
        "symbol": "TANSSIUSDT",
        "base_asset": "TANSSI",
        "quote_asset": "USDT",
        "price": 0.04431,
        "high_price": 0.0454,
        "low_price": 0.03921,
        "volume_24h": {
          "base_volume": 86213820.0,
          "quote_volume": 3650975.87747,
          "count": 74297
        },
        "change_24h": {
          "absolute": 0.00306,
          "percentage": 7.418
        },
        "open_price": 0.04125,
        "prev_close_price": 0.04125,
        "bid_price": 0.04436,
        "ask_price": 0.04443,
        "bid_qty": 576.0,
        "ask_qty": 726.0,
        "mark_price": 0.04431,
        "funding_rate": 5e-05,
        "next_funding_time": 1758888000000,
        "open_interest": 74297.0,
        "timestamp": 1758885814076,
        "market_cap": null,
        "circulating_supply": null,
        "market_cap_rank": null
      }
    },
    {
      "rank": 19,
      "symbol": "MILKUSDT",
      "market_data": {
        "symbol": "MILKUSDT",
        "base_asset": "MILK",
        "quote_asset": "USDT",
        "price": 0.04216,
        "high_price": 0.044,
        "low_price": 0.03864,
        "volume_24h": {
          "base_volume": 106436002.0,
          "quote_volume": 4422470.08679,
          "count": 64470
        },
        "change_24h": {
          "absolute": 0.00265,
          "percentage": 6.7
        },
        "open_price": 0.03955,
        "prev_close_price": 0.03955,
        "bid_price": 0.04218,
        "ask_price": 0.0422,
        "bid_qty": 485.0,
        "ask_qty": 125.0,
        "mark_price": 0.04217068,
        "funding_rate": 0.00067765,
        "next_funding_time": 1758888000000,
        "open_interest": 64470.0,
        "timestamp": 1758885814074,
        "market_cap": null,
        "circulating_supply": null,
        "market_cap_rank": null
      }
    },
    {
      "rank": 20,
      "symbol": "JELLYJELLYUSDT",
      "market_data": {
        "symbol": "JELLYJELLYUSDT",
        "base_asset": "JELLYJELLY",
        "quote_asset": "USDT",
        "price": 0.04726,
        "high_price": 0.04891,
        "low_price": 0.04298,
        "volume_24h": {
          "base_volume": 289486460.0,
          "quote_volume": 13302720.52633,
          "count": 146523
        },
        "change_24h": {
          "absolute": 0.00261,
          "percentage": 5.845
        },
        "open_price": 0.04465,
        "prev_close_price": 0.04465,
        "bid_price": 0.04727,
        "ask_price": 0.04728,
        "bid_qty": 1295.0,
        "ask_qty": 2435.0,
        "mark_price": 0.04725504,
        "funding_rate": 0.0002366,
        "next_funding_time": 1758888000000,
        "open_interest": 146523.0,
        "timestamp": 1758885814075,
        "market_cap": null,
        "circulating_supply": null,
        "market_cap_rank": null
      }
    },
    {
      "rank": 21,
      "symbol": "SOLVUSDT",
      "market_data": {
        "symbol": "SOLVUSDT",
        "base_asset": "SOLV",
        "quote_asset": "USDT",
        "price": "0.04314",
        "open_price": "0.04087",
        "high_price": "0.04658",
        "low_price": "0.04053",
        "prev_close_price": "0.04087",
        "change_1h": null,
        "change_4h": null,
        "change_12h": null,
        "change_24h": {
          "percentage": 5.628,
          "absolute": "0.0023"
        },
        "volume_24h": {
          "base_volume": "673404542.0",
          "quote_volume": "29440498.05615",
          "count": 321268
        },
        "funding_rate": "0.00019196",
        "next_funding_time": "2025-09-26 12:00:00+00:00",
        "open_interest": "321268.0",
        "mark_price": "0.04314",
        "index_price": null,
        "best_bid_price": null,
        "best_ask_price": null,
        "bid_qty": "28352.0",
        "ask_qty": "32409.0",
        "timestamp": "2025-09-26 11:23:34.074000+00:00"
      }
    },
    {
      "rank": 22,
      "symbol": "HUMAUSDT",
      "market_data": {
        "symbol": "HUMAUSDT",
        "base_asset": "HUMA",
        "quote_asset": "USDT",
        "price": "0.03468",
        "open_price": "0.03294",
        "high_price": "0.036355",
        "low_price": "0.031431",
        "prev_close_price": "0.03294",
        "change_1h": null,
        "change_4h": null,
        "change_12h": null,
        "change_24h": {
          "percentage": 5.288,
          "absolute": "0.001742"
        },
        "volume_24h": {
          "base_volume": "2409889875.0",
          "quote_volume": "82047356.170168",
          "count": 1570364
        },
        "funding_rate": "-0.00032433",
        "next_funding_time": "2025-09-26 12:00:00+00:00",
        "open_interest": "1570364.0",
        "mark_price": "0.034682",
        "index_price": null,
        "best_bid_price": null,
        "best_ask_price": null,
        "bid_qty": "12397.0",
        "ask_qty": "4750.0",
        "timestamp": "2025-09-26 11:23:34.076000+00:00"
      }
    },
    {
      "rank": 23,
      "symbol": "TUTUSDT",
      "market_data": {
        "symbol": "TUTUSDT",
        "base_asset": "TUT",
        "quote_asset": "USDT",
        "price": "0.08846",
        "open_price": "0.08425",
        "high_price": "0.09316",
        "low_price": "0.08064",
        "prev_close_price": "0.08425",
        "change_1h": null,
        "change_4h": null,
        "change_12h": null,
        "change_24h": {
          "percentage": 5.033,
          "absolute": "0.00424"
        },
        "volume_24h": {
          "base_volume": "1073915719.0",
          "quote_volume": "93752979.69106",
          "count": 1245532
        },
        "funding_rate": "0.00005",
        "next_funding_time": "2025-09-26 12:00:00+00:00",
        "open_interest": "1245532.0",
        "mark_price": "0.08846",
        "index_price": null,
        "best_bid_price": null,
        "best_ask_price": null,
        "bid_qty": "3229.0",
        "ask_qty": "474.0",
        "timestamp": "2025-09-26 11:23:34.076000+00:00"
      }
    },
    {
      "rank": 24,
      "symbol": "ALPINEUSDT",
      "market_data": {
        "symbol": "ALPINEUSDT",
        "base_asset": "ALPINE",
        "quote_asset": "USDT",
        "price": "2.1275",
        "open_price": "2.027",
        "high_price": "2.1971",
        "low_price": "1.9974",
        "prev_close_price": "2.027",
        "change_1h": null,
        "change_4h": null,
        "change_12h": null,
        "change_24h": {
          "percentage": 4.924,
          "absolute": "0.0998"
        },
        "volume_24h": {
          "base_volume": "5792581.5",
          "quote_volume": "12054719.66257",
          "count": 220340
        },
        "funding_rate": "0.00005",
        "next_funding_time": "2025-09-26 12:00:00+00:00",
        "open_interest": "220340.0",
        "mark_price": "2.12737029",
        "index_price": null,
        "best_bid_price": null,
        "best_ask_price": null,
        "bid_qty": "23.3",
        "ask_qty": "35.2",
        "timestamp": "2025-09-26 11:23:34.075000+00:00"
      }
    },
    {
      "rank": 25,
      "symbol": "BANKUSDT",
      "market_data": {
        "symbol": "BANKUSDT",
        "base_asset": "BANK",
        "quote_asset": "USDT",
        "price": "0.07716",
        "open_price": "0.07371",
        "high_price": "0.07925",
        "low_price": "0.07",
        "prev_close_price": "0.07371",
        "change_1h": null,
        "change_4h": null,
        "change_12h": null,
        "change_24h": {
          "percentage": 4.653,
          "absolute": "0.00343"
        },
        "volume_24h": {
          "base_volume": "69671060.0",
          "quote_volume": "5141084.70251",
          "count": 90544
        },
        "funding_rate": "0.00015324",
        "next_funding_time": "2025-09-26 12:00:00+00:00",
        "open_interest": "90544.0",
        "mark_price": "0.0771",
        "index_price": null,
        "best_bid_price": null,
        "best_ask_price": null,
        "bid_qty": "139.0",
        "ask_qty": "1296.0",
        "timestamp": "2025-09-26 11:23:34.073000+00:00"
      }
    },
    {
      "rank": 26,
      "symbol": "FLUIDUSDT",
      "market_data": {
        "symbol": "FLUIDUSDT",
        "base_asset": "FLUID",
        "quote_asset": "USDT",
        "price": "6.384",
        "open_price": "6.114",
        "high_price": "7.056",
        "low_price": "5.534",
        "prev_close_price": "6.114",
        "change_1h": null,
        "change_4h": null,
        "change_12h": null,
        "change_24h": {
          "percentage": 4.4,
          "absolute": "0.269"
        },
        "volume_24h": {
          "base_volume": "21909867.7",
          "quote_volume": "137738211.3349",
          "count": 1125557
        },
        "funding_rate": "-0.00018752",
        "next_funding_time": "2025-09-26 12:00:00+00:00",
        "open_interest": "1125557.0",
        "mark_price": "6.38755742",
        "index_price": null,
        "best_bid_price": null,
        "best_ask_price": null,
        "bid_qty": "2.3",
        "ask_qty": "72.9",
        "timestamp": "2025-09-26 11:23:34.075000+00:00"
      }
    },
    {
      "rank": 27,
      "symbol": "LAUSDT",
      "market_data": {
        "symbol": "LAUSDT",
        "base_asset": "LA",
        "quote_asset": "USDT",
        "price": "0.3843",
        "open_price": "0.3689",
        "high_price": "0.3902",
        "low_price": "0.3448",
        "prev_close_price": "0.3689",
        "change_1h": null,
        "change_4h": null,
        "change_12h": null,
        "change_24h": {
          "percentage": 4.202,
          "absolute": "0.0155"
        },
        "volume_24h": {
          "base_volume": "155058508.2",
          "quote_volume": "56216804.09041",
          "count": 474107
        },
        "funding_rate": "-0.00033738",
        "next_funding_time": "2025-09-26 12:00:00+00:00",
        "open_interest": "474107.0",
        "mark_price": "0.3851",
        "index_price": null,
        "best_bid_price": null,
        "best_ask_price": null,
        "bid_qty": "821.0",
        "ask_qty": "4257.5",
        "timestamp": "2025-09-26 11:23:34.074000+00:00"
      }
    },
    {
      "rank": 28,
      "symbol": "1000RATSUSDT",
      "market_data": {
        "symbol": "1000RATSUSDT",
        "base_asset": "1000RATS",
        "quote_asset": "USDT",
        "price": "0.0264",
        "open_price": "0.02537",
        "high_price": "0.02853",
        "low_price": "0.02518",
        "prev_close_price": "0.02537",
        "change_1h": null,
        "change_4h": null,
        "change_12h": null,
        "change_24h": {
          "percentage": 4.06,
          "absolute": "0.00103"
        },
        "volume_24h": {
          "base_volume": "565535165.0",
          "quote_volume": "15383535.96109",
          "count": 173541
        },
        "funding_rate": "0.00005",
        "next_funding_time": "2025-09-26 12:00:00+00:00",
        "open_interest": "173541.0",
        "mark_price": "0.0264",
        "index_price": null,
        "best_bid_price": null,
        "best_ask_price": null,
        "bid_qty": "45650.0",
        "ask_qty": "2203.0",
        "timestamp": "2025-09-26 11:23:34.075000+00:00"
      }
    },
    {
      "rank": 29,
      "symbol": "BRUSDT",
      "market_data": {
        "symbol": "BRUSDT",
        "base_asset": "BR",
        "quote_asset": "USDT",
        "price": "0.07732",
        "open_price": "0.07436",
        "high_price": "0.08209",
        "low_price": "0.07436",
        "prev_close_price": "0.07436",
        "change_1h": null,
        "change_4h": null,
        "change_12h": null,
        "change_24h": {
          "percentage": 3.981,
          "absolute": "0.00296"
        },
        "volume_24h": {
          "base_volume": "43989157.0",
          "quote_volume": "3451886.99873",
          "count": 53278
        },
        "funding_rate": "0.00005",
        "next_funding_time": "2025-09-26 12:00:00+00:00",
        "open_interest": "53278.0",
        "mark_price": "0.0773083",
        "index_price": null,
        "best_bid_price": null,
        "best_ask_price": null,
        "bid_qty": "4032.0",
        "ask_qty": "2219.0",
        "timestamp": "2025-09-26 11:23:34.073000+00:00"
      }
    },
    {
      "rank": 30,
      "symbol": "FISUSDT",
      "market_data": {
        "symbol": "FISUSDT",
        "base_asset": "FIS",
        "quote_asset": "USDT",
        "price": "0.08838",
        "open_price": "0.08539",
        "high_price": "0.09154",
        "low_price": "0.08142",
        "prev_close_price": "0.08539",
        "change_1h": null,
        "change_4h": null,
        "change_12h": null,
        "change_24h": {
          "percentage": 3.56,
          "absolute": "0.00304"
        },
        "volume_24h": {
          "base_volume": "50723706.0",
          "quote_volume": "4406309.4317",
          "count": 93985
        },
        "funding_rate": "0.00005",
        "next_funding_time": "2025-09-26 12:00:00+00:00",
        "open_interest": "93985.0",
        "mark_price": "0.08845518",
        "index_price": null,
        "best_bid_price": null,
        "best_ask_price": null,
        "bid_qty": "299.0",
        "ask_qty": "1120.0",
        "timestamp": "2025-09-26 11:23:34.075000+00:00"
      }
    },
    {
      "rank": 31,
      "symbol": "BASUSDT",
      "market_data": {
        "symbol": "BASUSDT",
        "base_asset": "BAS",
        "quote_asset": "USDT",
        "price": "0.014606",
        "open_price": "0.014128",
        "high_price": "0.015636",
        "low_price": "0.013713",
        "prev_close_price": "0.014128",
        "change_1h": null,
        "change_4h": null,
        "change_12h": null,
        "change_24h": {
          "percentage": 3.383,
          "absolute": "0.000478"
        },
        "volume_24h": {
          "base_volume": "1132348686.0",
          "quote_volume": "16589332.328549",
          "count": 380943
        },
        "funding_rate": "0.00049503",
        "next_funding_time": "2025-09-26 12:00:00+00:00",
        "open_interest": "380943.0",
        "mark_price": "0.014597",
        "index_price": null,
        "best_bid_price": null,
        "best_ask_price": null,
        "bid_qty": "3326.0",
        "ask_qty": "1678.0",
        "timestamp": "2025-09-26 11:23:34.076000+00:00"
      }
    },
    {
      "rank": 32,
      "symbol": "HEIUSDT",
      "market_data": {
        "symbol": "HEIUSDT",
        "base_asset": "HEI",
        "quote_asset": "USDT",
        "price": "0.3768",
        "open_price": "0.3655",
        "high_price": "0.395",
        "low_price": "0.3502",
        "prev_close_price": "0.3655",
        "change_1h": null,
        "change_4h": null,
        "change_12h": null,
        "change_24h": {
          "percentage": 3.092,
          "absolute": "0.0113"
        },
        "volume_24h": {
          "base_volume": "20142509.3",
          "quote_volume": "7637157.36768",
          "count": 123712
        },
        "funding_rate": "0.00005",
        "next_funding_time": "2025-09-26 12:00:00+00:00",
        "open_interest": "123712.0",
        "mark_price": "0.37689321",
        "index_price": null,
        "best_bid_price": null,
        "best_ask_price": null,
        "bid_qty": "483.5",
        "ask_qty": "28.2",
        "timestamp": "2025-09-26 11:23:34.076000+00:00"
      }
    },
    {
      "rank": 33,
      "symbol": "A2ZUSDT",
      "market_data": {
        "symbol": "A2ZUSDT",
        "base_asset": "A2Z",
        "quote_asset": "USDT",
        "price": "0.005421",
        "open_price": "0.005295",
        "high_price": "0.005679",
        "low_price": "0.00518",
        "prev_close_price": "0.005295",
        "change_1h": null,
        "change_4h": null,
        "change_12h": null,
        "change_24h": {
          "percentage": 2.38,
          "absolute": "0.000126"
        },
        "volume_24h": {
          "base_volume": "1997441447.0",
          "quote_volume": "10823400.423638",
          "count": 174488
        },
        "funding_rate": "0.00005",
        "next_funding_time": "2025-09-26 12:00:00+00:00",
        "open_interest": "174488.0",
        "mark_price": "0.00542185",
        "index_price": null,
        "best_bid_price": null,
        "best_ask_price": null,
        "bid_qty": "9260.0",
        "ask_qty": "4441.0",
        "timestamp": "2025-09-26 11:23:34.073000+00:00"
      }
    },
    {
      "rank": 34,
      "symbol": "B2USDT",
      "market_data": {
        "symbol": "B2USDT",
        "base_asset": "B2",
        "quote_asset": "USDT",
        "price": "0.7669",
        "open_price": "0.752",
        "high_price": "0.7699",
        "low_price": "0.6334",
        "prev_close_price": "0.752",
        "change_1h": null,
        "change_4h": null,
        "change_12h": null,
        "change_24h": {
          "percentage": 1.981,
          "absolute": "0.0149"
        },
        "volume_24h": {
          "base_volume": "13369108.0",
          "quote_volume": "9727379.7757",
          "count": 121501
        },
        "funding_rate": "0.00005",
        "next_funding_time": "2025-09-26 12:00:00+00:00",
        "open_interest": "121501.0",
        "mark_price": "0.7671898",
        "index_price": null,
        "best_bid_price": null,
        "best_ask_price": null,
        "bid_qty": "172.0",
        "ask_qty": "310.0",
        "timestamp": "2025-09-26 11:23:34.075000+00:00"
      }
    },
    {
      "rank": 35,
      "symbol": "OGUSDT",
      "market_data": {
        "symbol": "OGUSDT",
        "base_asset": "OG",
        "quote_asset": "USDT",
        "price": "17.552",
        "open_price": "17.216",
        "high_price": "18.198",
        "low_price": "16.612",
        "prev_close_price": "17.216",
        "change_1h": null,
        "change_4h": null,
        "change_12h": null,
        "change_24h": {
          "percentage": 1.952,
          "absolute": "0.336"
        },
        "volume_24h": {
          "base_volume": "1920875.6",
          "quote_volume": "33415957.4172",
          "count": 404539
        },
        "funding_rate": "0.00005",
        "next_funding_time": "2025-09-26 12:00:00+00:00",
        "open_interest": "404539.0",
        "mark_price": "17.555",
        "index_price": null,
        "best_bid_price": null,
        "best_ask_price": null,
        "bid_qty": "4.8",
        "ask_qty": "10.5",
        "timestamp": "2025-09-26 11:23:34.075000+00:00"
      }
    },
    {
      "rank": 36,
      "symbol": "WALUSDT",
      "market_data": {
        "symbol": "WALUSDT",
        "base_asset": "WAL",
        "quote_asset": "USDT",
        "price": "0.3751",
        "open_price": "0.3686",
        "high_price": "0.3847",
        "low_price": "0.3598",
        "prev_close_price": "0.3686",
        "change_1h": null,
        "change_4h": null,
        "change_12h": null,
        "change_24h": {
          "percentage": 1.763,
          "absolute": "0.0065"
        },
        "volume_24h": {
          "base_volume": "23292170.0",
          "quote_volume": "8664379.4373",
          "count": 84335
        },
        "funding_rate": "-0.0003712",
        "next_funding_time": "2025-09-26 12:00:00+00:00",
        "open_interest": "84335.0",
        "mark_price": "0.3752847",
        "index_price": null,
        "best_bid_price": null,
        "best_ask_price": null,
        "bid_qty": "727.0",
        "ask_qty": "545.0",
        "timestamp": "2025-09-26 11:23:34.075000+00:00"
      }
    },
    {
      "rank": 37,
      "symbol": "HIFIUSDT",
      "market_data": {
        "symbol": "HIFIUSDT",
        "base_asset": "HIFI",
        "quote_asset": "USDT",
        "price": "0.09402",
        "open_price": "0.0926",
        "high_price": "0.09727",
        "low_price": "0.0888",
        "prev_close_price": "0.0926",
        "change_1h": null,
        "change_4h": null,
        "change_12h": null,
        "change_24h": {
          "percentage": 1.62,
          "absolute": "0.0015"
        },
        "volume_24h": {
          "base_volume": "184763543.0",
          "quote_volume": "17164261.33725",
          "count": 241763
        },
        "funding_rate": "0.00027085",
        "next_funding_time": "2025-09-26 12:00:00+00:00",
        "open_interest": "241763.0",
        "mark_price": "0.09392",
        "index_price": null,
        "best_bid_price": null,
        "best_ask_price": null,
        "bid_qty": "714.0",
        "ask_qty": "1846.0",
        "timestamp": "2025-09-26 11:23:34.073000+00:00"
      }
    },
    {
      "rank": 38,
      "symbol": "WUSDT",
      "market_data": {
        "symbol": "WUSDT",
        "base_asset": "W",
        "quote_asset": "USDT",
        "price": "0.10017",
        "open_price": "0.09885",
        "high_price": "0.1086",
        "low_price": "0.09504",
        "prev_close_price": "0.09885",
        "change_1h": null,
        "change_4h": null,
        "change_12h": null,
        "change_24h": {
          "percentage": 1.345,
          "absolute": "0.00133"
        },
        "volume_24h": {
          "base_volume": "1161601968.4",
          "quote_volume": "118943689.969034",
          "count": 985669
        },
        "funding_rate": "0.00002425",
        "next_funding_time": "2025-09-26 12:00:00+00:00",
        "open_interest": "985669.0",
        "mark_price": "0.10021052",
        "index_price": null,
        "best_bid_price": null,
        "best_ask_price": null,
        "bid_qty": "3045.1",
        "ask_qty": "219.7",
        "timestamp": "2025-09-26 11:23:34.074000+00:00"
      }
    },
    {
      "rank": 39,
      "symbol": "MASKUSDT",
      "market_data": {
        "symbol": "MASKUSDT",
        "base_asset": "MASK",
        "quote_asset": "USDT",
        "price": "1.2107",
        "open_price": "1.1948",
        "high_price": "1.229",
        "low_price": "1.1687",
        "prev_close_price": "1.1948",
        "change_1h": null,
        "change_4h": null,
        "change_12h": null,
        "change_24h": {
          "percentage": 1.339,
          "absolute": "0.016"
        },
        "volume_24h": {
          "base_volume": "13713633.0",
          "quote_volume": "16453105.5213",
          "count": 187098
        },
        "funding_rate": "6E-7",
        "next_funding_time": "2025-09-26 12:00:00+00:00",
        "open_interest": "187098.0",
        "mark_price": "1.2107",
        "index_price": null,
        "best_bid_price": null,
        "best_ask_price": null,
        "bid_qty": "246.0",
        "ask_qty": "247.0",
        "timestamp": "2025-09-26 11:23:34.076000+00:00"
      }
    },
    {
      "rank": 40,
      "symbol": "ICNTUSDT",
      "market_data": {
        "symbol": "ICNTUSDT",
        "base_asset": "ICNT",
        "quote_asset": "USDT",
        "price": "0.194",
        "open_price": "0.1915",
        "high_price": "0.2027",
        "low_price": "0.1895",
        "prev_close_price": "0.1915",
        "change_1h": null,
        "change_4h": null,
        "change_12h": null,
        "change_24h": {
          "percentage": 1.305,
          "absolute": "0.0025"
        },
        "volume_24h": {
          "base_volume": "8579806.0",
          "quote_volume": "1685327.2596",
          "count": 23258
        },
        "funding_rate": "0.00007302",
        "next_funding_time": "2025-09-26 12:00:00+00:00",
        "open_interest": "23258.0",
        "mark_price": "0.19397091",
        "index_price": null,
        "best_bid_price": null,
        "best_ask_price": null,
        "bid_qty": "1755.0",
        "ask_qty": "821.0",
        "timestamp": "2025-09-26 11:23:34.074000+00:00"
      }
    },
    {
      "rank": 41,
      "symbol": "TWTUSDT",
      "market_data": {
        "symbol": "TWTUSDT",
        "base_asset": "TWT",
        "quote_asset": "USDT",
        "price": "1.1901",
        "open_price": "1.1769",
        "high_price": "1.2612",
        "low_price": "1.1533",
        "prev_close_price": "1.1769",
        "change_1h": null,
        "change_4h": null,
        "change_12h": null,
        "change_24h": {
          "percentage": 1.139,
          "absolute": "0.0134"
        },
        "volume_24h": {
          "base_volume": "31031385.0",
          "quote_volume": "37196719.0464",
          "count": 515012
        },
        "funding_rate": "0.00002091",
        "next_funding_time": "2025-09-26 12:00:00+00:00",
        "open_interest": "515012.0",
        "mark_price": "1.19020408",
        "index_price": null,
        "best_bid_price": null,
        "best_ask_price": null,
        "bid_qty": "188.0",
        "ask_qty": "35.0",
        "timestamp": "2025-09-26 11:23:34.073000+00:00"
      }
    },
    {
      "rank": 42,
      "symbol": "BTCDOMUSDT",
      "market_data": {
        "symbol": "BTCDOMUSDT",
        "base_asset": "BTCDOM",
        "quote_asset": "USDT",
        "price": "4134.5",
        "open_price": "4089.4",
        "high_price": "4250.0",
        "low_price": "4048.0",
        "prev_close_price": "4089.4",
        "change_1h": null,
        "change_4h": null,
        "change_12h": null,
        "change_24h": {
          "percentage": 1.103,
          "absolute": "45.1"
        },
        "volume_24h": {
          "base_volume": "4125.923",
          "quote_volume": "16926206.8",
          "count": 84561
        },
        "funding_rate": "0.00027473",
        "next_funding_time": "2025-09-26 16:00:00+00:00",
        "open_interest": "84561.0",
        "mark_price": "4134.5",
        "index_price": null,
        "best_bid_price": null,
        "best_ask_price": null,
        "bid_qty": "0.058",
        "ask_qty": "0.138",
        "timestamp": "2025-09-26 11:23:34.075000+00:00"
      }
    },
    {
      "rank": 43,
      "symbol": "PUNDIXUSDT",
      "market_data": {
        "symbol": "PUNDIXUSDT",
        "base_asset": "PUNDIX",
        "quote_asset": "USDT",
        "price": "0.3024",
        "open_price": "0.2997",
        "high_price": "0.3098",
        "low_price": "0.2916",
        "prev_close_price": "0.2997",
        "change_1h": null,
        "change_4h": null,
        "change_12h": null,
        "change_24h": {
          "percentage": 0.901,
          "absolute": "0.0027"
        },
        "volume_24h": {
          "base_volume": "10830548.0",
          "quote_volume": "3266255.4245",
          "count": 52173
        },
        "funding_rate": "0.00005",
        "next_funding_time": "2025-09-26 12:00:00+00:00",
        "open_interest": "52173.0",
        "mark_price": "0.30247333",
        "index_price": null,
        "best_bid_price": null,
        "best_ask_price": null,
        "bid_qty": "355.0",
        "ask_qty": "956.0",
        "timestamp": "2025-09-26 11:23:34.075000+00:00"
      }
    },
    {
      "rank": 44,
      "symbol": "TRXUSDT",
      "market_data": {
        "symbol": "TRXUSDT",
        "base_asset": "TRX",
        "quote_asset": "USDT",
        "price": "0.33369",
        "open_price": "0.33086",
        "high_price": "0.33603",
        "low_price": "0.32968",
        "prev_close_price": "0.33086",
        "change_1h": null,
        "change_4h": null,
        "change_12h": null,
        "change_24h": {
          "percentage": 0.855,
          "absolute": "0.00283"
        },
        "volume_24h": {
          "base_volume": "378148506.0",
          "quote_volume": "126060238.68964",
          "count": 296034
        },
        "funding_rate": "-0.00002899",
        "next_funding_time": "2025-09-26 16:00:00+00:00",
        "open_interest": "296034.0",
        "mark_price": "0.33372947",
        "index_price": null,
        "best_bid_price": null,
        "best_ask_price": null,
        "bid_qty": "3683.0",
        "ask_qty": "734.0",
        "timestamp": "2025-09-26 11:23:34.074000+00:00"
      }
    },
    {
      "rank": 45,
      "symbol": "HUSDT",
      "market_data": {
        "symbol": "HUSDT",
        "base_asset": "H",
        "quote_asset": "USDT",
        "price": "0.05087",
        "open_price": "0.05051",
        "high_price": "0.05188",
        "low_price": "0.04807",
        "prev_close_price": "0.05051",
        "change_1h": null,
        "change_4h": null,
        "change_12h": null,
        "change_24h": {
          "percentage": 0.713,
          "absolute": "0.00036"
        },
        "volume_24h": {
          "base_volume": "207075775.0",
          "quote_volume": "10381503.82103",
          "count": 134014
        },
        "funding_rate": "0.00005",
        "next_funding_time": "2025-09-26 12:00:00+00:00",
        "open_interest": "134014.0",
        "mark_price": "0.0508646",
        "index_price": null,
        "best_bid_price": null,
        "best_ask_price": null,
        "bid_qty": "371.0",
        "ask_qty": "3922.0",
        "timestamp": "2025-09-26 11:23:34.075000+00:00"
      }
    },
    {
      "rank": 46,
      "symbol": "KASUSDT",
      "market_data": {
        "symbol": "KASUSDT",
        "base_asset": "KAS",
        "quote_asset": "USDT",
        "price": "0.07655",
        "open_price": "0.07601",
        "high_price": "0.08016",
        "low_price": "0.07388",
        "prev_close_price": "0.07601",
        "change_1h": null,
        "change_4h": null,
        "change_12h": null,
        "change_24h": {
          "percentage": 0.71,
          "absolute": "0.00054"
        },
        "volume_24h": {
          "base_volume": "295388030.0",
          "quote_volume": "22714309.29199",
          "count": 197803
        },
        "funding_rate": "0.00005",
        "next_funding_time": "2025-09-26 12:00:00+00:00",
        "open_interest": "197803.0",
        "mark_price": "0.07655117",
        "index_price": null,
        "best_bid_price": null,
        "best_ask_price": null,
        "bid_qty": "4404.0",
        "ask_qty": "6296.0",
        "timestamp": "2025-09-26 11:23:34.073000+00:00"
      }
    },
    {
      "rank": 47,
      "symbol": "MOCAUSDT",
      "market_data": {
        "symbol": "MOCAUSDT",
        "base_asset": "MOCA",
        "quote_asset": "USDT",
        "price": "0.06811",
        "open_price": "0.0677",
        "high_price": "0.07061",
        "low_price": "0.06563",
        "prev_close_price": "0.0677",
        "change_1h": null,
        "change_4h": null,
        "change_12h": null,
        "change_24h": {
          "percentage": 0.606,
          "absolute": "0.00041"
        },
        "volume_24h": {
          "base_volume": "66469445.0",
          "quote_volume": "4576387.1648",
          "count": 53914
        },
        "funding_rate": "0.00005",
        "next_funding_time": "2025-09-26 12:00:00+00:00",
        "open_interest": "53914.0",
        "mark_price": "0.06811367",
        "index_price": null,
        "best_bid_price": null,
        "best_ask_price": null,
        "bid_qty": "1112.0",
        "ask_qty": "1401.0",
        "timestamp": "2025-09-26 11:23:34.073000+00:00"
      }
    },
    {
      "rank": 48,
      "symbol": "XPINUSDT",
      "market_data": {
        "symbol": "XPINUSDT",
        "base_asset": "XPIN",
        "quote_asset": "USDT",
        "price": "0.0008434",
        "open_price": "0.0008389",
        "high_price": "0.000861",
        "low_price": "0.0007623",
        "prev_close_price": "0.0008389",
        "change_1h": null,
        "change_4h": null,
        "change_12h": null,
        "change_24h": {
          "percentage": 0.548,
          "absolute": "0.0000046"
        },
        "volume_24h": {
          "base_volume": "23540304962.0",
          "quote_volume": "19246001.8101422",
          "count": 264173
        },
        "funding_rate": "0.00026662",
        "next_funding_time": "2025-09-26 12:00:00+00:00",
        "open_interest": "264173.0",
        "mark_price": "0.0008429",
        "index_price": null,
        "best_bid_price": null,
        "best_ask_price": null,
        "bid_qty": "35166.0",
        "ask_qty": "21182.0",
        "timestamp": "2025-09-26 11:23:34.073000+00:00"
      }
    },
    {
      "rank": 49,
      "symbol": "AIOUSDT",
      "market_data": {
        "symbol": "AIOUSDT",
        "base_asset": "AIO",
        "quote_asset": "USDT",
        "price": "0.15135",
        "open_price": "0.15065",
        "high_price": "0.15455",
        "low_price": "0.14343",
        "prev_close_price": "0.15065",
        "change_1h": null,
        "change_4h": null,
        "change_12h": null,
        "change_24h": {
          "percentage": 0.478,
          "absolute": "0.00072"
        },
        "volume_24h": {
          "base_volume": "21828619.0",
          "quote_volume": "3262725.50293",
          "count": 67452
        },
        "funding_rate": "0.00015852",
        "next_funding_time": "2025-09-26 12:00:00+00:00",
        "open_interest": "67452.0",
        "mark_price": "0.15135",
        "index_price": null,
        "best_bid_price": null,
        "best_ask_price": null,
        "bid_qty": "3.0",
        "ask_qty": "2197.0",
        "timestamp": "2025-09-26 11:23:34.074000+00:00"
      }
    },
    {
      "rank": 50,
      "symbol": "MERLUSDT",
      "market_data": {
        "symbol": "MERLUSDT",
        "base_asset": "MERL",
        "quote_asset": "USDT",
        "price": "0.291",
        "open_price": "0.2897",
        "high_price": "0.30971",
        "low_price": "0.2807",
        "prev_close_price": "0.2897",
        "change_1h": null,
        "change_4h": null,
        "change_12h": null,
        "change_24h": {
          "percentage": 0.449,
          "absolute": "0.0013"
        },
        "volume_24h": {
          "base_volume": "156105255.0",
          "quote_volume": "45469064.03965",
          "count": 652105
        },
        "funding_rate": "0.00005",
        "next_funding_time": "2025-09-26 12:00:00+00:00",
        "open_interest": "652105.0",
        "mark_price": "0.291",
        "index_price": null,
        "best_bid_price": null,
        "best_ask_price": null,
        "bid_qty": "431.0",
        "ask_qty": "2.0",
        "timestamp": "2025-09-26 11:23:34.074000+00:00"
      }
    },
    {
      "rank": 51,
      "symbol": "ATHUSDT",
      "market_data": {
        "symbol": "ATHUSDT",
        "base_asset": "ATH",
        "quote_asset": "USDT",
        "price": "0.05827",
        "open_price": "0.05803",
        "high_price": "0.06043",
        "low_price": "0.05404",
        "prev_close_price": "0.05803",
        "change_1h": null,
        "change_4h": null,
        "change_12h": null,
        "change_24h": {
          "percentage": 0.414,
          "absolute": "0.00024"
        },
        "volume_24h": {
          "base_volume": "775802961.0",
          "quote_volume": "44268790.65706",
          "count": 396057
        },
        "funding_rate": "-0.00010313",
        "next_funding_time": "2025-09-26 12:00:00+00:00",
        "open_interest": "396057.0",
        "mark_price": "0.05827",
        "index_price": null,
        "best_bid_price": null,
        "best_ask_price": null,
        "bid_qty": "753.0",
        "ask_qty": "930.0",
        "timestamp": "2025-09-26 11:23:34.076000+00:00"
      }
    },
    {
      "rank": 52,
      "symbol": "FORTHUSDT",
      "market_data": {
        "symbol": "FORTHUSDT",
        "base_asset": "FORTH",
        "quote_asset": "USDT",
        "price": "2.424",
        "open_price": "2.415",
        "high_price": "2.475",
        "low_price": "2.353",
        "prev_close_price": "2.415",
        "change_1h": null,
        "change_4h": null,
        "change_12h": null,
        "change_24h": {
          "percentage": 0.373,
          "absolute": "0.009"
        },
        "volume_24h": {
          "base_volume": "671084.8",
          "quote_volume": "1626551.7018",
          "count": 39666
        },
        "funding_rate": "-0.00010648",
        "next_funding_time": "2025-09-26 12:00:00+00:00",
        "open_interest": "39666.0",
        "mark_price": "2.4259594",
        "index_price": null,
        "best_bid_price": null,
        "best_ask_price": null,
        "bid_qty": "9.0",
        "ask_qty": "121.6",
        "timestamp": "2025-09-26 11:23:34.075000+00:00"
      }
    },
    {
      "rank": 53,
      "symbol": "SANTOSUSDT",
      "market_data": {
        "symbol": "SANTOSUSDT",
        "base_asset": "SANTOS",
        "quote_asset": "USDT",
        "price": "1.756",
        "open_price": "1.751",
        "high_price": "1.793",
        "low_price": "1.703",
        "prev_close_price": "1.751",
        "change_1h": null,
        "change_4h": null,
        "change_12h": null,
        "change_24h": {
          "percentage": 0.286,
          "absolute": "0.005"
        },
        "volume_24h": {
          "base_volume": "1690611.3",
          "quote_volume": "2959485.171",
          "count": 74815
        },
        "funding_rate": "0.00005",
        "next_funding_time": "2025-09-26 12:00:00+00:00",
        "open_interest": "74815.0",
        "mark_price": "1.756",
        "index_price": null,
        "best_bid_price": null,
        "best_ask_price": null,
        "bid_qty": "593.6",
        "ask_qty": "63.5",
        "timestamp": "2025-09-26 11:23:34.075000+00:00"
      }
    },
    {
      "rank": 54,
      "symbol": "BDXNUSDT",
      "market_data": {
        "symbol": "BDXNUSDT",
        "base_asset": "BDXN",
        "quote_asset": "USDT",
        "price": "0.03631",
        "open_price": "0.03623",
        "high_price": "0.03742",
        "low_price": "0.03412",
        "prev_close_price": "0.03623",
        "change_1h": null,
        "change_4h": null,
        "change_12h": null,
        "change_24h": {
          "percentage": 0.221,
          "absolute": "0.00008"
        },
        "volume_24h": {
          "base_volume": "83269679.0",
          "quote_volume": "2977016.79613",
          "count": 57170
        },
        "funding_rate": "0.00005174",
        "next_funding_time": "2025-09-26 12:00:00+00:00",
        "open_interest": "57170.0",
        "mark_price": "0.03628778",
        "index_price": null,
        "best_bid_price": null,
        "best_ask_price": null,
        "bid_qty": "4490.0",
        "ask_qty": "6601.0",
        "timestamp": "2025-09-26 11:23:34.073000+00:00"
      }
    },
    {
      "rank": 55,
      "symbol": "YALAUSDT",
      "market_data": {
        "symbol": "YALAUSDT",
        "base_asset": "YALA",
        "quote_asset": "USDT",
        "price": "0.0957",
        "open_price": "0.0956",
        "high_price": "0.1013",
        "low_price": "0.0924",
        "prev_close_price": "0.0956",
        "change_1h": null,
        "change_4h": null,
        "change_12h": null,
        "change_24h": {
          "percentage": 0.105,
          "absolute": "0.0001"
        },
        "volume_24h": {
          "base_volume": "79577336.0",
          "quote_volume": "7694702.9424",
          "count": 72856
        },
        "funding_rate": "0.00005",
        "next_funding_time": "2025-09-26 12:00:00+00:00",
        "open_interest": "72856.0",
        "mark_price": "0.09564994",
        "index_price": null,
        "best_bid_price": null,
        "best_ask_price": null,
        "bid_qty": "25353.0",
        "ask_qty": "2336.0",
        "timestamp": "2025-09-26 11:23:34.076000+00:00"
      }
    },
    {
      "rank": 56,
      "symbol": "CROSSUSDT",
      "market_data": {
        "symbol": "CROSSUSDT",
        "base_asset": "CROSS",
        "quote_asset": "USDT",
        "price": "0.22804",
        "open_price": "0.2279",
        "high_price": "0.23055",
        "low_price": "0.2182",
        "prev_close_price": "0.2279",
        "change_1h": null,
        "change_4h": null,
        "change_12h": null,
        "change_24h": {
          "percentage": 0.061,
          "absolute": "0.00014"
        },
        "volume_24h": {
          "base_volume": "17322628.0",
          "quote_volume": "3900092.97932",
          "count": 53086
        },
        "funding_rate": "0.00005",
        "next_funding_time": "2025-09-26 12:00:00+00:00",
        "open_interest": "53086.0",
        "mark_price": "0.22804",
        "index_price": null,
        "best_bid_price": null,
        "best_ask_price": null,
        "bid_qty": "725.0",
        "ask_qty": "67.0",
        "timestamp": "2025-09-26 11:23:34.075000+00:00"
      }
    },
    {
      "rank": 57,
      "symbol": "PAXGUSDT",
      "market_data": {
        "symbol": "PAXGUSDT",
        "base_asset": "PAXG",
        "quote_asset": "USDT",
        "price": "3754.75",
        "open_price": "3753.66",
        "high_price": "3764.14",
        "low_price": "3729.19",
        "prev_close_price": "3753.66",
        "change_1h": null,
        "change_4h": null,
        "change_12h": null,
        "change_24h": {
          "percentage": 0.029,
          "absolute": "1.1"
        },
        "volume_24h": {
          "base_volume": "21910.783",
          "quote_volume": "82141522.9542",
          "count": 182070
        },
        "funding_rate": "0.00005",
        "next_funding_time": "2025-09-26 12:00:00+00:00",
        "open_interest": "182070.0",
        "mark_price": "3754.75",
        "index_price": null,
        "best_bid_price": null,
        "best_ask_price": null,
        "bid_qty": "5.389",
        "ask_qty": "1.984",
        "timestamp": "2025-09-26 11:23:34.073000+00:00"
      }
    }
  ]
}